covpy/__init__.py
covpy/covpy.py
covpy/ignore-covpy.py
ingore-covpy/__init__.py
covpy-0.0.9.dist-info/LICENSE
covpy-0.0.9.dist-info/METADATA
covpy-0.0.9.dist-info/WHEEL
covpy-0.0.9.dist-info/top_level.txt
covpy-0.0.9.dist-info/RECORD
